[
    {
        "id": "106158814788583424",
        "name": "Inusame",
        "fans_total": "117056241",
        "fans_monthly": "22916372",
        "color": "blue",
        "rank_total": "20",
        "rank_monthly": "13",
        "daily_average": "1681984",
        "save_data": [
            {
                "label": "",
                "url": ""
            },
            {
                "label": "",
                "url": ""
            },
            {
                "label": "",
                "url": ""
            },
            {
                "label": "",
                "url": ""
            },
            {
                "label": "",
                "url": ""
            }
        ]
    },
    {
        "id": "217274197553053696",
        "name": "Vivi",
        "fans_total": "131853613",
        "fans_monthly": "23776192",
        "color": "blue",
        "rank_total": "12",
        "rank_monthly": "12",
        "daily_average": "1745092",
        "save_data": [
            {
                "label": "Daiwa Scarlet Gemini CM",
                "url": "https://alpha123.github.io/uma-tools/umalator-global/#H4sIAAAAAAAACqWRS2vDMBCE%2F8ucddBaVhzrlmPppZBj6UHEm9QktowemBLy34v8SEgvhfY2SKPZ2U9XHFzygV8aGJJbIoE%2B2G64cIDRUgoE5gam2JCutapULZACv7nwyjzARJ9YwNsDN3yEuaJzLtsFTt6lPqcKjGzjJ%2FtJB7bB9ZOMbceL1Tac58ubQOos5SCX4rGNuRdIyloSBMIwlSGSOSnaru0tTEVKYHBjnlBTKXBKMcCoUgmMbWhcB6N0kV94G%2Fn0BYM992eXINC0Idr%2BwLshtjHlGtjlSckf7dPpHo%2BAn%2BZze7kEmPfcVNa5aS1lMVUupCRdzKKgVWwWodYrtV3MupoF0XJCShM%2BZjDFb2Bk%2BQRmQ3cwVbVdwUzf%2BgBT%2FhPM7s9g8mbP25dq4aFXVHceM4bbNwMVWY6xAgAA"
            },
            {
                "label": "",
                "url": ""
            },
            {
                "label": "test",
                "url": "test"
            },
            {
                "label": "",
                "url": ""
            },
            {
                "label": "",
                "url": ""
            }
        ]
    },
    {
        "id": "355642968150900737",
        "name": "Moot",
        "fans_total": "122495480",
        "fans_monthly": "22210649",
        "color": "green",
        "rank_total": "18",
        "rank_monthly": "17",
        "daily_average": "1630186",
        "save_data": [
            {
                "label": "",
                "url": ""
            },
            {
                "label": "",
                "url": ""
            },
            {
                "label": "",
                "url": ""
            },
            {
                "label": "",
                "url": ""
            },
            {
                "label": "",
                "url": ""
            }
        ]
    },
    {
        "id": "811499544524619807",
        "name": "Banana",
        "fans_total": "93456048",
        "fans_monthly": "18942506",
        "color": "green",
        "rank_total": "29",
        "rank_monthly": "24",
        "daily_average": "1390316",
        "save_data": [
            {
                "label": "",
                "url": ""
            },
            {
                "label": "",
                "url": ""
            },
            {
                "label": "",
                "url": ""
            },
            {
                "label": "",
                "url": ""
            },
            {
                "label": "",
                "url": ""
            }
        ]
    },
    {
        "id": "265291353615761410",
        "name": "zzz",
        "fans_total": "168720025",
        "fans_monthly": "28391823",
        "color": "blue",
        "rank_total": "3",
        "rank_monthly": "7",
        "daily_average": "2083864",
        "save_data": [
            {
                "label": "golshi gemini",
                "url": "https://alpha123.github.io/uma-tools/umalator-global/#H4sIAAAAAAAACp2Qu04DMRBF%2F%2BXWLjzeZ9xRIgqQUqIUVnYSrGTXKz8UoSj%2FjrzxUgRo6I7H87g6V%2Bxd8oGfB2iSPZHAFMw4nzlAN1IKBOYBWrXUbJqqqzYCKfCbCy%2FMM3T0iQW82fPAB%2BgrRudyu8DRuzTlrQIXNvGD%2FcKBTXDTgtGOXFrNwPm%2BvAmk0VBe5FI82JhzgaTsJEEgzEsYUkuwaEY7GWiiTSUwu0s%2B0VFemGKArpte4GLD4EZo1Xd5xJvIx09ovNqTGy0EBhuimfb8NEcbU86Bp3wq%2BYP5WS0LHssnez4H6PccVXY5qpKSVqiqFZoCba0WoLWHqC%2BgVPmq10rTlkpLhN1dkXpQ9Lec5Vnk9JmLnIyrnPo%2B8i1ny9PJpd%2FlbP8tZ3e7fQFSLc8SbwIAAA%3D%3D"
            },
            {
                "label": "taishin gemini",
                "url": "https://alpha123.github.io/uma-tools/umalator-global/#H4sIAAAAAAAACq2Qu24CMRBF%2F%2BXWLjz7YnFHGVEkEmVEYbEDscDrlR9CEeLfI%2B%2BDBOp0x1fjmatzw8ElH%2FitgyLZEgn0QdvhwgGqllIgMHdQRUP1ui5X5VogBf5wYcs8QEWfWMDrA3d8hLrBOpfHBU7epT5vFbiyjl%2FsRw6sg%2BtHjMbyPKo7zvflXSBZTXmRS%2FFoYu4FkrWUBIEwjGWI1rlY1Nb0Oj%2BpEBjcNZ8YG55SDFDVqhG4mtA5C1W2Vf7ideTTNxTezdlZA4HOhKj7A2%2BGaGLKPbDLp5I%2F6qd0g98Fr%2FHZXC4B6hMkZT1WLaSkcoF6hnJJykfSFhM01ZQQtTNU8ww1tEBF2E%2BKihdFf%2BQU8knO%2BJzltJlnORkXOdX05SFnx%2F3Zpf%2BWs7%2FffwCC6%2FWwbwIAAA%3D%3D"
            },
            {
                "label": "",
                "url": ""
            },
            {
                "label": "",
                "url": ""
            },
            {
                "label": "",
                "url": ""
            }
        ]
    },
    {
        "id": "167102753989066752",
        "name": "rice",
        "fans_total": "94188785",
        "fans_monthly": "16381465",
        "color": "yellow",
        "rank_total": "27",
        "rank_monthly": "27",
        "daily_average": "1202344",
        "save_data": [
            {
                "label": "",
                "url": ""
            },
            {
                "label": "",
                "url": ""
            },
            {
                "label": "",
                "url": ""
            },
            {
                "label": "",
                "url": ""
            },
            {
                "label": "",
                "url": ""
            }
        ]
    },
    {
        "id": "296147291566374914",
        "name": "Flac",
        "fans_total": "119759517",
        "fans_monthly": "21512967",
        "color": "green",
        "rank_total": "19",
        "rank_monthly": "19",
        "daily_average": "1578979",
        "save_data": [
            {
                "label": "",
                "url": ""
            },
            {
                "label": "",
                "url": ""
            },
            {
                "label": "",
                "url": ""
            },
            {
                "label": "",
                "url": ""
            },
            {
                "label": "",
                "url": ""
            }
        ]
    },
    {
        "id": "77781522408538112",
        "name": "Nightfish",
        "fans_total": "155158000",
        "fans_monthly": "26058178",
        "color": "blue",
        "rank_total": "4",
        "rank_monthly": "9",
        "daily_average": "1912582",
        "save_data": [
            {
                "label": "",
                "url": ""
            },
            {
                "label": "",
                "url": ""
            },
            {
                "label": "",
                "url": ""
            },
            {
                "label": "",
                "url": ""
            },
            {
                "label": "",
                "url": ""
            }
        ]
    },
    {
        "id": "306827300073373707",
        "name": "luuuc",
        "fans_total": "93660561",
        "fans_monthly": "16990825",
        "color": "yellow",
        "rank_total": "28",
        "rank_monthly": "26",
        "daily_average": "1247069",
        "save_data": [
            {
                "label": "",
                "url": ""
            },
            {
                "label": "",
                "url": ""
            },
            {
                "label": "",
                "url": ""
            },
            {
                "label": "",
                "url": ""
            },
            {
                "label": "",
                "url": ""
            }
        ]
    },
    {
        "id": "409587819661492224",
        "name": "D'1ne",
        "fans_total": "99132109",
        "fans_monthly": "32247632",
        "color": "blue",
        "rank_total": "24",
        "rank_monthly": "3",
        "daily_average": "2366867",
        "save_data": [
            {
                "label": "",
                "url": ""
            },
            {
                "label": "",
                "url": ""
            },
            {
                "label": "",
                "url": ""
            },
            {
                "label": "",
                "url": ""
            },
            {
                "label": "",
                "url": ""
            }
        ]
    },
    {
        "id": "335829406146625547",
        "name": "Rudder",
        "fans_total": "110985820",
        "fans_monthly": "17487343",
        "color": "green",
        "rank_total": "23",
        "rank_monthly": "25",
        "daily_average": "1283512",
        "save_data": [
            {
                "label": "",
                "url": ""
            },
            {
                "label": "",
                "url": ""
            },
            {
                "label": "",
                "url": ""
            },
            {
                "label": "",
                "url": ""
            },
            {
                "label": "",
                "url": ""
            }
        ]
    },
    {
        "id": "174017194013753346",
        "name": "Chyai",
        "fans_total": "97586631",
        "fans_monthly": "19836161",
        "color": "green",
        "rank_total": "25",
        "rank_monthly": "23",
        "daily_average": "1455907",
        "save_data": [
            {
                "label": "",
                "url": ""
            },
            {
                "label": "",
                "url": ""
            },
            {
                "label": "",
                "url": ""
            },
            {
                "label": "",
                "url": ""
            },
            {
                "label": "",
                "url": ""
            }
        ]
    },
    {
        "id": "215062981250121731",
        "name": "Allxtend",
        "fans_total": "263564161",
        "fans_monthly": "61853791",
        "color": "purple",
        "rank_total": "1",
        "rank_monthly": "1",
        "daily_average": "4539859",
        "save_data": [
            {
                "label": "",
                "url": ""
            },
            {
                "label": "",
                "url": ""
            },
            {
                "label": "",
                "url": ""
            },
            {
                "label": "",
                "url": ""
            },
            {
                "label": "",
                "url": ""
            }
        ]
    },
    {
        "id": "967921401577242705",
        "name": "plnk",
        "fans_total": "139227108",
        "fans_monthly": "31301941",
        "color": "blue",
        "rank_total": "9",
        "rank_monthly": "5",
        "daily_average": "2297457",
        "save_data": [
            {
                "label": "yay",
                "url": "https://store.steampowered.com/app/1315270/PEE_WAR/"
            },
            {
                "label": "",
                "url": ""
            },
            {
                "label": "",
                "url": ""
            },
            {
                "label": "",
                "url": ""
            },
            {
                "label": "",
                "url": ""
            }
        ]
    },
    {
        "id": "327458365053861897",
        "name": "Paganist",
        "fans_total": "129104645",
        "fans_monthly": "21482338",
        "color": "green",
        "rank_total": "15",
        "rank_monthly": "20",
        "daily_average": "1576731",
        "save_data": [
            {
                "label": "",
                "url": ""
            },
            {
                "label": "",
                "url": ""
            },
            {
                "label": "",
                "url": ""
            },
            {
                "label": "",
                "url": ""
            },
            {
                "label": "",
                "url": ""
            }
        ]
    },
    {
        "id": "346257862915260418",
        "name": "Trid",
        "fans_total": "75208236",
        "fans_monthly": "13072750",
        "color": "red",
        "rank_total": "30",
        "rank_monthly": "28",
        "daily_average": "959496",
        "save_data": [
            {
                "label": "",
                "url": ""
            },
            {
                "label": "",
                "url": ""
            },
            {
                "label": "",
                "url": ""
            },
            {
                "label": "",
                "url": ""
            },
            {
                "label": "",
                "url": ""
            }
        ]
    },
    {
        "id": "141593372040232960",
        "name": "IcyShadow",
        "fans_total": "129129874",
        "fans_monthly": "22315598",
        "color": "green",
        "rank_total": "14",
        "rank_monthly": "16",
        "daily_average": "1637889",
        "save_data": [
            {
                "label": "",
                "url": ""
            },
            {
                "label": "",
                "url": ""
            },
            {
                "label": "",
                "url": ""
            },
            {
                "label": "",
                "url": ""
            },
            {
                "label": "",
                "url": ""
            }
        ]
    },
    {
        "id": "134421068709363714",
        "name": "Caladerbo",
        "fans_total": "127968860",
        "fans_monthly": "25177771",
        "color": "blue",
        "rank_total": "16",
        "rank_monthly": "11",
        "daily_average": "1847963",
        "save_data": [
            {
                "label": "",
                "url": ""
            },
            {
                "label": "",
                "url": ""
            },
            {
                "label": "",
                "url": ""
            },
            {
                "label": "",
                "url": ""
            },
            {
                "label": "",
                "url": ""
            }
        ]
    },
    {
        "id": "322776542826594314",
        "name": "SirPsycho",
        "fans_total": "94584799",
        "fans_monthly": "30433475",
        "color": "blue",
        "rank_total": "26",
        "rank_monthly": "6",
        "daily_average": "2233714",
        "save_data": [
            {
                "label": "",
                "url": ""
            },
            {
                "label": "",
                "url": ""
            },
            {
                "label": "",
                "url": ""
            },
            {
                "label": "",
                "url": ""
            },
            {
                "label": "",
                "url": ""
            }
        ]
    },
    {
        "id": "220047711137824769",
        "name": "MasajMacaulk",
        "fans_total": "130274564",
        "fans_monthly": "21351464",
        "color": "green",
        "rank_total": "13",
        "rank_monthly": "21",
        "daily_average": "1567125",
        "save_data": [
            {
                "label": "",
                "url": ""
            },
            {
                "label": "",
                "url": ""
            },
            {
                "label": "",
                "url": ""
            },
            {
                "label": "",
                "url": ""
            },
            {
                "label": "",
                "url": ""
            }
        ]
    },
    {
        "id": "694195078633357313",
        "name": "NoRest",
        "fans_total": "111859683",
        "fans_monthly": "20679553",
        "color": "green",
        "rank_total": "22",
        "rank_monthly": "22",
        "daily_average": "1517809",
        "save_data": [
            {
                "label": "",
                "url": ""
            },
            {
                "label": "",
                "url": ""
            },
            {
                "label": "",
                "url": ""
            },
            {
                "label": "",
                "url": ""
            },
            {
                "label": "",
                "url": ""
            }
        ]
    },
    {
        "id": "229279100513157120",
        "name": "Ryukaze",
        "fans_total": "136743214",
        "fans_monthly": "22445678",
        "color": "blue",
        "rank_total": "10",
        "rank_monthly": "15",
        "daily_average": "1647437",
        "save_data": [
            {
                "label": "",
                "url": ""
            },
            {
                "label": "",
                "url": ""
            },
            {
                "label": "",
                "url": ""
            },
            {
                "label": "",
                "url": ""
            },
            {
                "label": "",
                "url": ""
            }
        ]
    },
    {
        "id": "242247483684552706",
        "name": "Babu",
        "fans_total": "147413450",
        "fans_monthly": "22208272",
        "color": "green",
        "rank_total": "8",
        "rank_monthly": "18",
        "daily_average": "1630012",
        "save_data": [
            {
                "label": "",
                "url": ""
            },
            {
                "label": "",
                "url": ""
            },
            {
                "label": "",
                "url": ""
            },
            {
                "label": "",
                "url": ""
            },
            {
                "label": "",
                "url": ""
            }
        ]
    },
    {
        "id": "301224730122387456",
        "name": "Noa",
        "fans_total": "174228197",
        "fans_monthly": "33098786",
        "color": "blue",
        "rank_total": "2",
        "rank_monthly": "2",
        "daily_average": "2429339",
        "save_data": [
            {
                "label": "",
                "url": ""
            },
            {
                "label": "",
                "url": ""
            },
            {
                "label": "",
                "url": ""
            },
            {
                "label": "",
                "url": ""
            },
            {
                "label": "",
                "url": ""
            }
        ]
    },
    {
        "id": "108335779918385152",
        "name": "Lost",
        "fans_total": "149110423",
        "fans_monthly": "26001673",
        "color": "blue",
        "rank_total": "7",
        "rank_monthly": "10",
        "daily_average": "1908435",
        "save_data": [
            {
                "label": "",
                "url": ""
            },
            {
                "label": "",
                "url": ""
            },
            {
                "label": "",
                "url": ""
            },
            {
                "label": "",
                "url": ""
            },
            {
                "label": "",
                "url": ""
            }
        ]
    },
    {
        "id": "140757170521112576",
        "name": "Halfwrong",
        "fans_total": "126662838",
        "fans_monthly": "22843924",
        "color": "blue",
        "rank_total": "17",
        "rank_monthly": "14",
        "daily_average": "1809476",
        "save_data": [
            {
                "label": "",
                "url": ""
            },
            {
                "label": "",
                "url": ""
            },
            {
                "label": "",
                "url": ""
            },
            {
                "label": "",
                "url": ""
            },
            {
                "label": "",
                "url": ""
            }
        ]
    },
    {
        "id": "109515996351430656",
        "name": "Flashwire",
        "fans_total": "150201420",
        "fans_monthly": "32176519",
        "color": "blue",
        "rank_total": "6",
        "rank_monthly": "4",
        "daily_average": "2361648",
        "save_data": [
            {
                "label": "",
                "url": ""
            },
            {
                "label": "",
                "url": ""
            },
            {
                "label": "",
                "url": ""
            },
            {
                "label": "",
                "url": ""
            },
            {
                "label": "",
                "url": ""
            }
        ]
    },
    {
        "id": "236889503615156226",
        "name": "Parzival",
        "fans_total": "133647544",
        "fans_monthly": "26561591",
        "color": "blue",
        "rank_total": "11",
        "rank_monthly": "8",
        "daily_average": "2103954",
        "save_data": [
            {
                "label": "",
                "url": ""
            },
            {
                "label": "",
                "url": ""
            },
            {
                "label": "",
                "url": ""
            },
            {
                "label": "",
                "url": ""
            },
            {
                "label": "",
                "url": ""
            }
        ]
    },
    {
        "id": "246327374390624257",
        "name": "Honchkrow",
        "fans_total": "152480042",
        "fans_monthly": "11242659",
        "color": "red",
        "rank_total": "5",
        "rank_monthly": "30",
        "daily_average": "1352564",
        "save_data": [
            {
                "label": "",
                "url": ""
            },
            {
                "label": "",
                "url": ""
            },
            {
                "label": "",
                "url": ""
            },
            {
                "label": "",
                "url": ""
            },
            {
                "label": "",
                "url": ""
            }
        ]
    },
    {
        "id": "308291753994354688",
        "name": "wooper",
        "fans_total": "115587405",
        "fans_monthly": "11978919",
        "color": "red",
        "rank_total": "21",
        "rank_monthly": "29",
        "daily_average": "1455736",
        "save_data": [
            {
                "label": "",
                "url": ""
            },
            {
                "label": "",
                "url": ""
            },
            {
                "label": "",
                "url": ""
            },
            {
                "label": "",
                "url": ""
            },
            {
                "label": "",
                "url": ""
            }
        ]
    },
    {
        "id": "00000000000000000",
        "name": "Stats",
        "fans_total": "",
        "fans_monthly": "",
        "color": "purple",
        "rank_total": "",
        "rank_monthly": "",
        "daily_average": "1642663",
        "fans_median": "22380638",
        "fans_guild_total": "722978815"
    }
]